speedclickpro_postinstall.py
speedclickpro/__init__.py
speedclickpro/__main__.py
speedclickpro/auto_clicker.py
speedclickpro/create_icon.py
speedclickpro/languages.py
speedclickpro/main.py
speedclickpro/icons/icon.png
speedclickpro/icons/logo.png
speedclickpro-1.0.7.data/scripts/speedclickpro
speedclickpro-1.0.7.data/scripts/speedclickpro.bat
speedclickpro-1.0.7.dist-info/licenses/LICENSE
speedclickpro-1.0.7.dist-info/METADATA
speedclickpro-1.0.7.dist-info/WHEEL
speedclickpro-1.0.7.dist-info/entry_points.txt
speedclickpro-1.0.7.dist-info/top_level.txt
speedclickpro-1.0.7.dist-info/RECORD
