Metadata-Version: 2.4
Name: speedclickpro
Version: 1.0.7
Summary: Advanced auto-clicker with animation sequencing capabilities
Home-page: https://github.com/yourusername/speedclickpro
Author: SpeedClick Pro Team
Author-email: your.email@example.com
Project-URL: Bug Tracker, https://github.com/yourusername/speedclickpro/issues
Classifier: Programming Language :: Python :: 3
Classifier: License :: OSI Approved :: MIT License
Classifier: Operating System :: Microsoft :: Windows
Classifier: Topic :: Utilities
Classifier: Intended Audience :: End Users/Desktop
Requires-Python: >=3.7
License-File: LICENSE
Requires-Dist: pyautogui>=0.9.54
Requires-Dist: keyboard>=0.13.5
Requires-Dist: Pillow>=10.0.0
Dynamic: author
Dynamic: author-email
Dynamic: classifier
Dynamic: description
Dynamic: description-content-type
Dynamic: home-page
Dynamic: license-file
Dynamic: project-url
Dynamic: requires-dist
Dynamic: requires-python
Dynamic: summary
